.gitignore
.readthedocs.yaml
.travis.yml
AUTHORS
CHANGELOG
CHANGES.txt
LICENSE
MANIFEST.in
README
README.rst
changelog.py
conftest.py
package-lock.json
package.json
pytest.ini
release.sh
select2.build.js
setup.py
tox.ini
.openshift/README.md
.openshift/action_hooks/README.md
.openshift/action_hooks/deploy
.openshift/cron/README.cron
.openshift/cron/hourly/reset_database
docs/Makefile
docs/api.rst
docs/conf.py
docs/genericm2m.rst
docs/gfk.rst
docs/gm2m.rst
docs/index.rst
docs/install.rst
docs/requirements.txt
docs/tagging.rst
docs/taggit.rst
docs/tutorial.rst
docs/_ext/djangodocs.py
docs/img/all.png
docs/img/autocomplete.png
docs/img/create_option.png
docs/img/created_option.png
docs/img/mine.png
docs/img/view.png
src/__init__.py
src/dal/__init__.py
src/dal/autocomplete.py
src/dal/forms.py
src/dal/forward.py
src/dal/views.py
src/dal/widgets.py
src/dal/static/autocomplete_light/autocomplete_light.js
src/dal/static/autocomplete_light/autocomplete_light.min.js
src/dal/static/autocomplete_light/autocomplete_light.min.js.map
src/dal/static/autocomplete_light/i18n/af.js
src/dal/static/autocomplete_light/i18n/ar.js
src/dal/static/autocomplete_light/i18n/az.js
src/dal/static/autocomplete_light/i18n/bg.js
src/dal/static/autocomplete_light/i18n/bn.js
src/dal/static/autocomplete_light/i18n/bs.js
src/dal/static/autocomplete_light/i18n/ca.js
src/dal/static/autocomplete_light/i18n/cs.js
src/dal/static/autocomplete_light/i18n/da.js
src/dal/static/autocomplete_light/i18n/de.js
src/dal/static/autocomplete_light/i18n/dsb.js
src/dal/static/autocomplete_light/i18n/el.js
src/dal/static/autocomplete_light/i18n/en.js
src/dal/static/autocomplete_light/i18n/eo.js
src/dal/static/autocomplete_light/i18n/es.js
src/dal/static/autocomplete_light/i18n/et.js
src/dal/static/autocomplete_light/i18n/eu.js
src/dal/static/autocomplete_light/i18n/fa.js
src/dal/static/autocomplete_light/i18n/fi.js
src/dal/static/autocomplete_light/i18n/fr.js
src/dal/static/autocomplete_light/i18n/gl.js
src/django_autocomplete_light.egg-info/PKG-INFO
src/django_autocomplete_light.egg-info/SOURCES.txt
src/django_autocomplete_light.egg-info/dependency_links.txt
src/django_autocomplete_light.egg-info/not-zip-safe
src/django_autocomplete_light.egg-info/requires.txt
src/django_autocomplete_light.egg-info/top_level.txt
