Metadata-Version: 2.2
Name: django-autocomplete-light
Version: 3.12.1
Summary: Fresh autocompletes for Django
Home-page: http://django-autocomplete-light.rtfd.org
Author: James Pic
Author-email: jamespic@gmail.com
License: MIT
Project-URL: Source, https://github.com/yourlabs/django-autocomplete-light
Keywords: django autocomplete
Classifier: Development Status :: 5 - Production/Stable
Classifier: Environment :: Web Environment
Classifier: Framework :: Django
Classifier: Framework :: Django :: 3.2
Classifier: Framework :: Django :: 4.0
Classifier: Framework :: Django :: 4.1
Classifier: Framework :: Django :: 4.2
Classifier: Framework :: Django :: 5.0
Classifier: Framework :: Django :: 5.1
Classifier: Intended Audience :: Developers
Classifier: License :: OSI Approved :: MIT License
Classifier: Operating System :: OS Independent
Classifier: Programming Language :: Python
Classifier: Programming Language :: Python :: 3
Classifier: Topic :: Internet :: WWW/HTTP
Classifier: Topic :: Software Development :: Libraries :: Python Modules
License-File: LICENSE
License-File: AUTHORS
Requires-Dist: django>=3.2
Provides-Extra: nested
Requires-Dist: django-nested-admin>=3.0.21; extra == "nested"
Provides-Extra: tags
Requires-Dist: django-taggit; extra == "tags"
Provides-Extra: genericm2m
Requires-Dist: django-generic-m2m; extra == "genericm2m"
Provides-Extra: gfk
Requires-Dist: django-querysetsequence>=0.11; extra == "gfk"
Dynamic: author
Dynamic: author-email
Dynamic: classifier
Dynamic: description
Dynamic: home-page
Dynamic: keywords
Dynamic: license
Dynamic: project-url
Dynamic: provides-extra
Dynamic: requires-dist
Dynamic: summary
